README.md
setup.py
django_duration_log/__init__.py
django_duration_log/apps.py
django_duration_log/middlewares.py
django_duration_log/utils.py
django_duration_log.egg-info/PKG-INFO
django_duration_log.egg-info/SOURCES.txt
django_duration_log.egg-info/dependency_links.txt
django_duration_log.egg-info/requires.txt
django_duration_log.egg-info/top_level.txt