Metadata-Version: 2.1
Name: django-duration-log
Version: 0.0.4
Summary: A Duration Log Tool for Django
Home-page: https://www.oren.ink/
Author: Oren Zhang
Author-email: oren_zhang@outlook.com
License: UNKNOWN
Platform: UNKNOWN
